tests/__init__.py
tests/test_timezones.py
timezones_lib/__init__.py
timezones_lib/cli.py
timezones_lib-1.0.0.dist-info/METADATA
timezones_lib-1.0.0.dist-info/WHEEL
timezones_lib-1.0.0.dist-info/entry_points.txt
timezones_lib-1.0.0.dist-info/top_level.txt
timezones_lib-1.0.0.dist-info/RECORD
