Metadata-Version: 2.4
Name: timezones-lib
Version: 1.0.0
Summary: Get current time in different timezones (PST, BST, WAT, CET, EST)
Home-page: https://github.com/username/timezones-lib
Author: TimezoneLib
Author-email: TimezoneLib <info@timezonelib.com>
License: MIT
Project-URL: Homepage, https://github.com/username/timezones-lib
Project-URL: Bug Reports, https://github.com/username/timezones-lib/issues
Project-URL: Source, https://github.com/username/timezones-lib
Keywords: timezone,time,cli,pytz
Classifier: Development Status :: 4 - Beta
Classifier: Intended Audience :: Developers
Classifier: License :: OSI Approved :: MIT License
Classifier: Programming Language :: Python :: 3
Classifier: Programming Language :: Python :: 3.8
Classifier: Programming Language :: Python :: 3.9
Classifier: Programming Language :: Python :: 3.10
Classifier: Programming Language :: Python :: 3.11
Requires-Python: >=3.8
Requires-Dist: pytz>=2023.3
Dynamic: author
Dynamic: home-page
Dynamic: requires-python
